marsdevs_reviewer/__init__.py
marsdevs_reviewer/cli.py
marsdevs_reviewer/debug.py
marsdevs_reviewer/reviewer.py
marsdevs_reviewer/learning/__init__.py
marsdevs_reviewer/learning/convention_extractor.py
marsdevs_reviewer/learning/learning_manager.py
marsdevs_reviewer/learning/models.py
marsdevs_reviewer/learning/pattern_matcher.py
tests/__init__.py
tests/test_reviewer.py
marsdevs_reviewer-1.1.1.dist-info/LICENSE.bak
marsdevs_reviewer-1.1.1.dist-info/METADATA
marsdevs_reviewer-1.1.1.dist-info/WHEEL
marsdevs_reviewer-1.1.1.dist-info/entry_points.txt
marsdevs_reviewer-1.1.1.dist-info/top_level.txt
marsdevs_reviewer-1.1.1.dist-info/RECORD
