Metadata-Version: 2.1
Name: marsdevs-reviewer
Version: 1.1.1
Summary: AI-powered code review tool that learns from your repository
Home-page: https://github.com/marsdevs/marsdevs-reviewer
Author: MarsDevs Team
Author-email: team@marsdevs.com
License: MIT
Project-URL: Bug Tracker, https://github.com/marsdevs/marsdevs-reviewer/issues
Project-URL: Documentation, https://github.com/marsdevs/marsdevs-reviewer#readme
Keywords: git pre-commit code-review ai conventions linting
Classifier: Development Status :: 4 - Beta
Classifier: Intended Audience :: Developers
Classifier: Topic :: Software Development :: Quality Assurance
Classifier: Topic :: Software Development :: Version Control :: Git
Classifier: Programming Language :: Python :: 3
Classifier: Programming Language :: Python :: 3.7
Classifier: Programming Language :: Python :: 3.8
Classifier: Programming Language :: Python :: 3.9
Classifier: Programming Language :: Python :: 3.10
Classifier: Programming Language :: Python :: 3.11
Classifier: Operating System :: OS Independent
Requires-Python: >=3.7
Requires-Dist: requests>=2.25.0
